affine6p/__init__.py
affine6p/affine6p.py
affine6p/estimate.py
affine6p/transform.py
affine6p-1.0.0.dist-info/METADATA
affine6p-1.0.0.dist-info/RECORD
affine6p-1.0.0.dist-info/WHEEL
affine6p-1.0.0.dist-info/top_level.txt
