Metadata-Version: 2.1
Name: affine6p
Version: 1.0.0
Summary: The Python affine6p lib to estimate affine transformation parameters between two sets of 2D points
Home-page: https://gitlab.com/yoshimoto/affine6p-py
Author: Masahiro Yoshimoto
Author-email: yoshimoto@flab.phys.nagoya-u.ac.jp
License: MIT
Keywords: calculate affine transformation six parameters
Platform: UNKNOWN
Classifier: Development Status :: 5 - Production/Stable
Classifier: Intended Audience :: Developers
Classifier: Intended Audience :: Science/Research
Classifier: License :: OSI Approved :: MIT License
Classifier: Operating System :: OS Independent
Classifier: Programming Language :: Python :: 2
Classifier: Programming Language :: Python :: 3
Classifier: Topic :: Scientific/Engineering :: Image Recognition
Classifier: Topic :: Scientific/Engineering :: Mathematics
Classifier: Topic :: Scientific/Engineering :: Physics
